huaweicloudsdkbcc/__init__.py
huaweicloudsdkbcc/v1/__init__.py
huaweicloudsdkbcc/v1/bcc_async_client.py
huaweicloudsdkbcc/v1/bcc_client.py
huaweicloudsdkbcc/v1/model/__init__.py
huaweicloudsdkbcc/v1/model/alarm_entity.py
huaweicloudsdkbcc/v1/model/alarm_namespace_enum.py
huaweicloudsdkbcc/v1/model/alarm_rule_entity.py
huaweicloudsdkbcc/v1/model/alarm_status_enum.py
huaweicloudsdkbcc/v1/model/alarm_type_enum.py
huaweicloudsdkbcc/v1/model/backup_compliance_rule.py
huaweicloudsdkbcc/v1/model/backup_compliance_rule_local_backup_frequency.py
huaweicloudsdkbcc/v1/model/bcc_organization_policy.py
huaweicloudsdkbcc/v1/model/bcc_organization_policy_detail.py
huaweicloudsdkbcc/v1/model/bcc_organization_policy_detail_policy_operation_definition.py
huaweicloudsdkbcc/v1/model/bcc_policy.py
huaweicloudsdkbcc/v1/model/bcc_policy_associate_vault.py
huaweicloudsdkbcc/v1/model/bcc_vault_day_summary.py
huaweicloudsdkbcc/v1/model/bcc_vault_single_summary.py
huaweicloudsdkbcc/v1/model/bind_compliance_body.py
huaweicloudsdkbcc/v1/model/bind_resource_level_compliance_request.py
huaweicloudsdkbcc/v1/model/bind_resource_level_compliance_response.py
huaweicloudsdkbcc/v1/model/cbr_policy_detail.py
huaweicloudsdkbcc/v1/model/cbr_policy_detail_resource_detail.py
huaweicloudsdkbcc/v1/model/cbr_vault_detail.py
huaweicloudsdkbcc/v1/model/cbr_vault_detail_resource_detail.py
huaweicloudsdkbcc/v1/model/change_resources_level_request.py
huaweicloudsdkbcc/v1/model/change_resources_level_response.py
huaweicloudsdkbcc/v1/model/compliance_rule.py
huaweicloudsdkbcc/v1/model/compliance_rule_local_backup_frequency.py
huaweicloudsdkbcc/v1/model/configure_protection_body.py
huaweicloudsdkbcc/v1/model/configure_vault_item.py
huaweicloudsdkbcc/v1/model/create_bcc_policy_request_body.py
huaweicloudsdkbcc/v1/model/create_bcc_policy_request_body_policy.py
huaweicloudsdkbcc/v1/model/create_bcc_policy_request_body_policy_cbr_policy_detail.py
huaweicloudsdkbcc-1.0.0.dist-info/METADATA
huaweicloudsdkbcc-1.0.0.dist-info/WHEEL
huaweicloudsdkbcc-1.0.0.dist-info/licenses/LICENSE
huaweicloudsdkbcc-1.0.0.dist-info/RECORD
